{
  "swagger" : "2.0",
  "info" : {
    "version" : "1.0",
    "title" : "tweeter-api"
  },
  "host" : "ie1aofz86k.execute-api.us-east-1.amazonaws.com",
  "basePath" : "/prod",
  "schemes" : [ "https" ],
  "paths" : {
    "/feed" : {
      "post" : {
        "description" : " Retrieves a paginated feed of status updates from users that the authenticated user follows",
        "responses" : { }
      },
      "options" : {
        "summary" : "CORS support",
        "consumes" : [ "application/json" ],
        "produces" : [ "application/json" ],
        "responses" : {
          "200" : {
            "description" : "Default response for CORS method",
            "headers" : {
              "Access-Control-Allow-Origin" : {
                "type" : "string"
              },
              "Access-Control-Allow-Methods" : {
                "type" : "string"
              },
              "Access-Control-Allow-Headers" : {
                "type" : "string"
              }
            }
          }
        }
      }
    },
    "/follow" : {
      "post" : {
        "description" : "Creates a follow relationship between the authenticated user and a target user",
        "responses" : { }
      },
      "options" : {
        "summary" : "CORS support",
        "consumes" : [ "application/json" ],
        "produces" : [ "application/json" ],
        "responses" : {
          "200" : {
            "description" : "Default response for CORS method",
            "headers" : {
              "Access-Control-Allow-Origin" : {
                "type" : "string"
              },
              "Access-Control-Allow-Methods" : {
                "type" : "string"
              },
              "Access-Control-Allow-Headers" : {
                "type" : "string"
              }
            }
          }
        }
      }
    },
    "/followee-count" : {
      "post" : {
        "description" : "Returns the total number of users that the specified user follows",
        "responses" : { }
      },
      "options" : {
        "summary" : "CORS support",
        "consumes" : [ "application/json" ],
        "produces" : [ "application/json" ],
        "responses" : {
          "200" : {
            "description" : "Default response for CORS method",
            "headers" : {
              "Access-Control-Allow-Origin" : {
                "type" : "string"
              },
              "Access-Control-Allow-Methods" : {
                "type" : "string"
              },
              "Access-Control-Allow-Headers" : {
                "type" : "string"
              }
            }
          }
        }
      }
    },
    "/followees" : {
      "post" : {
        "description" : "Retrieves a paginated list of users that the specified user follows",
        "responses" : { }
      },
      "options" : {
        "summary" : "CORS support",
        "consumes" : [ "application/json" ],
        "produces" : [ "application/json" ],
        "responses" : {
          "200" : {
            "description" : "Default response for CORS method",
            "headers" : {
              "Access-Control-Allow-Origin" : {
                "type" : "string"
              },
              "Access-Control-Allow-Methods" : {
                "type" : "string"
              },
              "Access-Control-Allow-Headers" : {
                "type" : "string"
              }
            }
          }
        }
      }
    },
    "/follower-count" : {
      "post" : {
        "description" : "Returns the total number of followers for the specified user",
        "responses" : { }
      },
      "options" : {
        "summary" : "CORS support",
        "consumes" : [ "application/json" ],
        "produces" : [ "application/json" ],
        "responses" : {
          "200" : {
            "description" : "Default response for CORS method",
            "headers" : {
              "Access-Control-Allow-Origin" : {
                "type" : "string"
              },
              "Access-Control-Allow-Methods" : {
                "type" : "string"
              },
              "Access-Control-Allow-Headers" : {
                "type" : "string"
              }
            }
          }
        }
      }
    },
    "/followers" : {
      "post" : {
        "description" : "Retrieves a paginated list of users who follow the specified user",
        "responses" : { }
      },
      "options" : {
        "summary" : "CORS support",
        "consumes" : [ "application/json" ],
        "produces" : [ "application/json" ],
        "responses" : {
          "200" : {
            "description" : "Default response for CORS method",
            "headers" : {
              "Access-Control-Allow-Origin" : {
                "type" : "string"
              },
              "Access-Control-Allow-Methods" : {
                "type" : "string"
              },
              "Access-Control-Allow-Headers" : {
                "type" : "string"
              }
            }
          }
        }
      }
    },
    "/is-follower" : {
      "post" : {
        "description" : "Checks whether the authenticated user is currently following a specified user",
        "responses" : { }
      },
      "options" : {
        "summary" : "CORS support",
        "consumes" : [ "application/json" ],
        "produces" : [ "application/json" ],
        "responses" : {
          "200" : {
            "description" : "Default response for CORS method",
            "headers" : {
              "Access-Control-Allow-Origin" : {
                "type" : "string"
              },
              "Access-Control-Allow-Methods" : {
                "type" : "string"
              },
              "Access-Control-Allow-Headers" : {
                "type" : "string"
              }
            }
          }
        }
      }
    },
    "/login" : {
      "post" : {
        "description" : "Authenticates a user with username and password, returns user profile and auth token",
        "responses" : { }
      },
      "options" : {
        "summary" : "CORS support",
        "consumes" : [ "application/json" ],
        "produces" : [ "application/json" ],
        "responses" : {
          "200" : {
            "description" : "Default response for CORS method",
            "headers" : {
              "Access-Control-Allow-Origin" : {
                "type" : "string"
              },
              "Access-Control-Allow-Methods" : {
                "type" : "string"
              },
              "Access-Control-Allow-Headers" : {
                "type" : "string"
              }
            }
          }
        }
      }
    },
    "/logout" : {
      "post" : {
        "description" : "Logs out a user by invalidating their authentication token",
        "responses" : { }
      },
      "options" : {
        "summary" : "CORS support",
        "consumes" : [ "application/json" ],
        "produces" : [ "application/json" ],
        "responses" : {
          "200" : {
            "description" : "Default response for CORS method",
            "headers" : {
              "Access-Control-Allow-Origin" : {
                "type" : "string"
              },
              "Access-Control-Allow-Methods" : {
                "type" : "string"
              },
              "Access-Control-Allow-Headers" : {
                "type" : "string"
              }
            }
          }
        }
      }
    },
    "/register" : {
      "post" : {
        "description" : "Registers a new user account with username, password, and profile information",
        "responses" : { }
      },
      "options" : {
        "summary" : "CORS support",
        "consumes" : [ "application/json" ],
        "produces" : [ "application/json" ],
        "responses" : {
          "200" : {
            "description" : "Default response for CORS method",
            "headers" : {
              "Access-Control-Allow-Origin" : {
                "type" : "string"
              },
              "Access-Control-Allow-Methods" : {
                "type" : "string"
              },
              "Access-Control-Allow-Headers" : {
                "type" : "string"
              }
            }
          }
        }
      }
    },
    "/status" : {
      "post" : {
        "responses" : { }
      },
      "options" : {
        "summary" : "CORS support",
        "consumes" : [ "application/json" ],
        "produces" : [ "application/json" ],
        "responses" : {
          "200" : {
            "description" : "Default response for CORS method",
            "headers" : {
              "Access-Control-Allow-Origin" : {
                "type" : "string"
              },
              "Access-Control-Allow-Methods" : {
                "type" : "string"
              },
              "Access-Control-Allow-Headers" : {
                "type" : "string"
              }
            }
          }
        }
      }
    },
    "/story" : {
      "post" : {
        "description" : "Retrieves a paginated list of status updates posted by the specified user",
        "responses" : { }
      },
      "options" : {
        "summary" : "CORS support",
        "consumes" : [ "application/json" ],
        "produces" : [ "application/json" ],
        "responses" : {
          "200" : {
            "description" : "Default response for CORS method",
            "headers" : {
              "Access-Control-Allow-Origin" : {
                "type" : "string"
              },
              "Access-Control-Allow-Methods" : {
                "type" : "string"
              },
              "Access-Control-Allow-Headers" : {
                "type" : "string"
              }
            }
          }
        }
      }
    },
    "/unfollow" : {
      "post" : {
        "description" : "Removes a follow relationship between the authenticated user and a target user",
        "responses" : { }
      },
      "options" : {
        "summary" : "CORS support",
        "consumes" : [ "application/json" ],
        "produces" : [ "application/json" ],
        "responses" : {
          "200" : {
            "description" : "Default response for CORS method",
            "headers" : {
              "Access-Control-Allow-Origin" : {
                "type" : "string"
              },
              "Access-Control-Allow-Methods" : {
                "type" : "string"
              },
              "Access-Control-Allow-Headers" : {
                "type" : "string"
              }
            }
          }
        }
      }
    },
    "/user" : {
      "post" : {
        "description" : "Retrieves user profile information by username or alias",
        "responses" : { }
      },
      "options" : {
        "summary" : "CORS support",
        "consumes" : [ "application/json" ],
        "produces" : [ "application/json" ],
        "responses" : {
          "200" : {
            "description" : "Default response for CORS method",
            "headers" : {
              "Access-Control-Allow-Origin" : {
                "type" : "string"
              },
              "Access-Control-Allow-Methods" : {
                "type" : "string"
              },
              "Access-Control-Allow-Headers" : {
                "type" : "string"
              }
            }
          }
        }
      }
    }
  }
}